[
  {
    "display_title": "A Origem",
    "aliases": ["A Origem", "Inception"]
  },
  {
    "display_title": "Batman: O Cavaleiro Das Trevas",
    "aliases": ["Batman O Cavaleiro Das Trevas", "The Dark Knight", "Batman O Cavaleiro das Trevas Ressurge"]
  },
  {
    "display_title": "Star Wars: Uma Nova Esperança",
    "aliases": ["Star Wars Uma Nova Esperança", "Star Wars Episodio IV", "Guerra nas Estrelas"]
  },
  {
    "display_title": "O Poderoso Chefão",
    "aliases": ["O Poderoso Chefão", "The Godfather"]
  },
  {
    "display_title": "De Volta para o Futuro",
    "aliases": ["De Volta para o Futuro", "Back to the Future"]
  },
  {
    "display_title": "Matrix",
    "aliases": ["Matrix", "The Matrix"]
  },
  {
    "display_title": "Forrest Gump",
    "aliases": ["Forrest Gump", "Forrest Gump O Contador de Historias"]
  },
  {
    "display_title": "O Senhor dos Anéis: A Sociedade do Anel",
    "aliases": ["O Senhor dos Anéis A Sociedade do Anel", "The Lord of the Rings The Fellowship of the Ring", "Senhor dos Aneis"]
  },
  {
    "display_title": "Pulp Fiction: Tempo de Violência",
    "aliases": ["Pulp Fiction", "Pulp Fiction Tempo de Violencia"]
  },
  {
    "display_title": "Clube da Luta",
    "aliases": ["Clube da Luta", "Fight Club"]
  },
  {
    "display_title": "Interestelar",
    "aliases": ["Interestelar", "Interstellar"]
  },
  {
    "display_title": "O Silêncio dos Inocentes",
    "aliases": ["O Silêncio dos Inocentes", "The Silence of the Lambs"]
  },
  {
    "display_title": "Cidade de Deus",
    "aliases": ["Cidade de Deus", "City of God"]
  },
  {
    "display_title": "Parasita",
    "aliases": ["Parasita", "Parasite", "Gisaengchung"]
  },
  {
    "display_title": "A Viagem de Chihiro",
    "aliases": ["A Viagem de Chihiro", "Spirited Away", "Sen to Chihiro no Kamikakushi"]
  },
  {
    "display_title": "Gladiador",
    "aliases": ["Gladiador", "Gladiator"]
  },
  {
    "display_title": "O Rei Leão",
    "aliases": ["O Rei Leão", "The Lion King"]
  },
  {
    "display_title": "Jurassic Park: O Parque dos Dinossauros",
    "aliases": ["Jurassic Park", "O Parque dos Dinossauros"]
  },
  {
    "display_title": "O Iluminado",
    "aliases": ["O Iluminado", "The Shining"]
  },
  {
    "display_title": "Psicose",
    "aliases": ["Psicose", "Psycho"]
  },
  {
    "display_title": "Toy Story",
    "aliases": ["Toy Story"]
  },
  {
    "display_title": "Up - Altas Aventuras",
    "aliases": ["Up Altas Aventuras", "Up"]
  },
  {
    "display_title": "WALL-E",
    "aliases": ["Wall-E", "Wall E"]
  },
  {
    "display_title": "O Show de Truman",
    "aliases": ["O Show de Truman", "The Truman Show"]
  },
  {
    "display_title": "Blade Runner: O Caçador de Androides",
    "aliases": ["Blade Runner", "Blade Runner O Cacador de Androides"]
  },
  {
    "display_title": "O Exterminador do Futuro 2: O Julgamento Final",
    "aliases": ["O Exterminador do Futuro 2", "Terminator 2 Judgment Day", "O Exterminador do Futuro 2 O Julgamento Final"]
  },
  {
    "display_title": "Alien, o Oitavo Passageiro",
    "aliases": ["Alien o Oitavo Passageiro", "Alien"]
  },
  {
    "display_title": "Duro de Matar",
    "aliases": ["Duro de Matar", "Die Hard"]
  },
  {
    "display_title": "Curtindo a Vida Adoidado",
    "aliases": ["Curtindo a Vida Adoidado", "Ferris Buellers Day Off"]
  },
  {
    "display_title": "Esqueceram de Mim",
    "aliases": ["Esqueceram de Mim", "Home Alone"]
  },
  {
    "display_title": "Homem-Aranha no Aranhaverso",
    "aliases": ["Homem Aranha no Aranhaverso", "Spider-Man Into the Spider-Verse"]
  },
  {
    "display_title": "O Sexto Sentido",
    "aliases": ["O Sexto Sentido", "The Sixth Sense"]
  },
  {
    "display_title": "Kill Bill: Volume 1",
    "aliases": ["Kill Bill Volume 1", "Kill Bill Vol 1"]
  }
]